odoo/addons/mrp_component_operation_scrap_reason/README.rst
odoo/addons/mrp_component_operation_scrap_reason/__init__.py
odoo/addons/mrp_component_operation_scrap_reason/__manifest__.py
odoo/addons/mrp_component_operation_scrap_reason/i18n/it.po
odoo/addons/mrp_component_operation_scrap_reason/i18n/mrp_component_operation_scrap_reason.pot
odoo/addons/mrp_component_operation_scrap_reason/readme/CONTRIBUTORS.rst
odoo/addons/mrp_component_operation_scrap_reason/readme/DESCRIPTION.rst
odoo/addons/mrp_component_operation_scrap_reason/static/description/icon.png
odoo/addons/mrp_component_operation_scrap_reason/static/description/index.html
odoo/addons/mrp_component_operation_scrap_reason/wizards/__init__.py
odoo/addons/mrp_component_operation_scrap_reason/wizards/mrp_component_operate.py
odoo/addons/mrp_component_operation_scrap_reason/wizards/mrp_component_operate_wizard.xml
odoo14_addon_mrp_component_operation_scrap_reason-14.0.1.1.0.dist-info/METADATA
odoo14_addon_mrp_component_operation_scrap_reason-14.0.1.1.0.dist-info/WHEEL
odoo14_addon_mrp_component_operation_scrap_reason-14.0.1.1.0.dist-info/top_level.txt
odoo14_addon_mrp_component_operation_scrap_reason-14.0.1.1.0.dist-info/RECORD
